streamlit_message/__init__.py
streamlit_message/frontend/build/asset-manifest.json
streamlit_message/frontend/build/bootstrap.min.css
streamlit_message/frontend/build/bootstrap.min.css.map
streamlit_message/frontend/build/index.html
streamlit_message/frontend/build/precache-manifest.78fa46ced5c94fc12f30a1513e18588e.js
streamlit_message/frontend/build/service-worker.js
streamlit_message/frontend/build/static/js/2.f0499c68.chunk.js
streamlit_message/frontend/build/static/js/2.f0499c68.chunk.js.LICENSE.txt
streamlit_message/frontend/build/static/js/2.f0499c68.chunk.js.map
streamlit_message/frontend/build/static/js/main.bd83c092.chunk.js
streamlit_message/frontend/build/static/js/main.bd83c092.chunk.js.map
streamlit_message/frontend/build/static/js/runtime-main.11ec9aca.js
streamlit_message/frontend/build/static/js/runtime-main.11ec9aca.js.map
streamlit_message-0.0.1.dist-info/LICENSE
streamlit_message-0.0.1.dist-info/METADATA
streamlit_message-0.0.1.dist-info/WHEEL
streamlit_message-0.0.1.dist-info/top_level.txt
streamlit_message-0.0.1.dist-info/RECORD
