Metadata-Version: 2.1
Name: streamlit-message
Version: 0.0.1
Summary: A streamlit component, to make chat ui messages
Home-page: https://github.com/gamcoh/st-message
Author: Gamliel Cohen <gamcoh>
Author-email: cohengamliel8@gmail.com
Keywords: chat message ui streamlit streamlit-component
Classifier: Programming Language :: Python :: 3
Classifier: Operating System :: OS Independent
Requires-Python: >=3.8
License-File: LICENSE
Requires-Dist: streamlit (>=0.63)
